ditainer-1.2.3.dist-info/METADATA
ditainer-1.2.3.dist-info/WHEEL
ditainer-1.2.3.dist-info/entry_points.txt
ditainer-1.2.3.dist-info/licenses/LICENSE
ditainer/__init__.py
ditainer/container.py
ditainer/exception/__init__.py
ditainer/exception/instance_manager.py
ditainer/exception/loader.py
ditainer/exception/service.py
ditainer/instance_manager.py
ditainer/loader/__init__.py
ditainer/loader/loader.py
ditainer/loader/yaml_loader.py
ditainer/service/__init__.py
ditainer/service/service.py
ditainer/service/service_arguments.py
ditainer/service/service_class.py
ditainer/service/service_factory.py
ditainer/service/service_id.py
ditainer/service/service_module.py
ditainer/service/service_tags.py
ditainer-1.2.3.dist-info/RECORD
