Metadata-Version: 2.1
Name: ditainer
Version: 1.2.3
Summary: Dependency Injection Container for Python
Author-Email: =?utf-8?q?Dami=C3=A1n_Ontivero?= <damian.ontivero.dev@gmail.com>
License: MIT
Requires-Python: <3.14,>=3.12
Requires-Dist: pyyaml>=6.0.2
